hlib/__init__.py
hlib/graph/__init__.py
hlib/graph/graph.py
hlib/graph_algorithms/__init__.py
hlib/graph_algorithms/search.py
hlib/tests/__init__.py
hlib/tests/test_graph/__init__.py
hlib/tests/test_graph/test_graph.py
hlib/tests/test_graph_algorithms/__init__.py
hlib/tests/test_graph_algorithms/test_graph_search.py
hlib-0.1.0.dist-info/LICENSE
hlib-0.1.0.dist-info/METADATA
hlib-0.1.0.dist-info/WHEEL
hlib-0.1.0.dist-info/top_level.txt
hlib-0.1.0.dist-info/RECORD
